mi.cp311-win_amd64.pyd
pymi-1.0.8.dist-info/licenses/AUTHORS
pymi-1.0.8.dist-info/licenses/LICENSE
wmi/__init__.py
wmi/samples/benchmark.py
wmi/samples/benchmark2.py
wmi/samples/benchmark3.py
wmi/samples/custom_operation_options.py
wmi/tests/__init__.py
wmi/tests/functional/__init__.py
wmi/tests/functional/test_base.py
wmi/tests/functional/test_basic_ops.py
wmi/tests/functional/test_timeouts.py
pymi-1.0.8.dist-info/METADATA
pymi-1.0.8.dist-info/WHEEL
pymi-1.0.8.dist-info/pbr.json
pymi-1.0.8.dist-info/top_level.txt
pymi-1.0.8.dist-info/RECORD
